odoo/addons/stock_viewer/__init__.py
odoo/addons/stock_viewer/__manifest__.py
odoo/addons/stock_viewer/security/ir.model.access.csv
odoo/addons/stock_viewer/security/stock_security.xml
odoo/addons/stock_viewer/static/description/icon.png
odoo/addons/stock_viewer/views/stock.xml
odoo12_addon_stock_viewer-12.0.1.0.0.99.dev3.dist-info/METADATA
odoo12_addon_stock_viewer-12.0.1.0.0.99.dev3.dist-info/WHEEL
odoo12_addon_stock_viewer-12.0.1.0.0.99.dev3.dist-info/top_level.txt
odoo12_addon_stock_viewer-12.0.1.0.0.99.dev3.dist-info/RECORD
